{
    "control": [
        { "VTOY_DEFAULT_MENU_MODE": "0" },
        { "VTOY_TREE_VIEW_MENU_STYLE": "0" },
        { "VTOY_FILT_DOT_UNDERSCORE_FILE": "1" },
        { "VTOY_SORT_CASE_SENSITIVE": "0" },
        { "VTOY_MAX_SEARCH_LEVEL": "max" },
        { "VTOY_DEFAULT_SEARCH_ROOT": "/ISO" },
        { "VTOY_MENU_TIMEOUT": "10" },
        { "VTOY_DEFAULT_IMAGE": "F4>Search and boot Windows" },
        { "VTOY_FILE_FLT_EFI": "1" },
        { "VTOY_DEFAULT_KBD_LAYOUT": "AZERTY" },
        { "VTOY_WIN11_BYPASS_CHECK": "0" },
        { "VTOY_HELP_TXT_LANGUAGE": "en_US" },
        { "VTOY_LINUX_REMOUNT": "0" }
    ]
}
